bank_scrapers/__init__.py
bank_scrapers/api_wrappers/__init__.py
bank_scrapers/api_wrappers/kraken/__init__.py
bank_scrapers/api_wrappers/kraken/driver.py
bank_scrapers/cli/__init__.py
bank_scrapers/cli/cli.py
bank_scrapers/common/__init__.py
bank_scrapers/common/functions.py
bank_scrapers/common/log.py
bank_scrapers/common/types.py
bank_scrapers/crypto/__init__.py
bank_scrapers/crypto/bitcoin/__init__.py
bank_scrapers/crypto/bitcoin/driver.py
bank_scrapers/crypto/ethereum/__init__.py
bank_scrapers/crypto/ethereum/driver.py
bank_scrapers/docs/scripts/version_badge.py
bank_scrapers/examples/prometheus_exporter/bank_exporter.py
bank_scrapers/get_accounts_info/__init__.py
bank_scrapers/get_accounts_info/driver.py
bank_scrapers/scrapers/__init__.py
bank_scrapers/scrapers/becu/__init__.py
bank_scrapers/scrapers/becu/driver.py
bank_scrapers/scrapers/chase/__init__.py
bank_scrapers/scrapers/chase/driver.py
bank_scrapers/scrapers/chase/mfa_auth.py
bank_scrapers/scrapers/common/__init__.py
bank_scrapers/scrapers/common/functions.py
bank_scrapers/scrapers/common/mfa_auth.py
bank_scrapers/scrapers/fidelity_netbenefits/__init__.py
bank_scrapers/scrapers/fidelity_netbenefits/driver.py
bank_scrapers/scrapers/roundpoint/__init__.py
bank_scrapers/scrapers/roundpoint/driver.py
bank_scrapers/scrapers/smbc_prestia/__init__.py
bank_scrapers/scrapers/smbc_prestia/driver.py
bank_scrapers/scrapers/uhfcu/__init__.py
bank_scrapers/scrapers/uhfcu/driver.py
bank_scrapers/scrapers/vanguard/__init__.py
bank_scrapers/scrapers/vanguard/driver.py
bank_scrapers/scrapers/zillow/__init__.py
bank_scrapers/scrapers/zillow/driver.py
bank_scrapers-1.4.21.dist-info/licenses/LICENSE
bank_scrapers-1.4.21.dist-info/METADATA
bank_scrapers-1.4.21.dist-info/WHEEL
bank_scrapers-1.4.21.dist-info/entry_points.txt
bank_scrapers-1.4.21.dist-info/top_level.txt
bank_scrapers-1.4.21.dist-info/RECORD
