Metadata-Version: 2.4
Name: bank_scrapers
Version: 1.4.21
Summary: Library for working with bank_scrapers drivers.
Author: Eric Bette
License: MIT License
Project-URL: homepage, https://github.com/eebette/bank_scrapers/tree/master
Requires-Python: >=3.8
License-File: LICENSE
Requires-Dist: pandas>=2.0.2
Requires-Dist: setuptools>=69.5.1
Requires-Dist: lxml>=5.2.2
Requires-Dist: yfinance>=0.2.65
Requires-Dist: web3>=7.0.0b6
Requires-Dist: PyVirtualDisplay>=3.0
Requires-Dist: pybadges>=3.0.1
Requires-Dist: prometheus_client>=0.20.0
Requires-Dist: CurrencyConverter>=0.17.23
Requires-Dist: patchright>=1.52.5
Dynamic: license-file
